pycalibration/__init__.py
pycalibration/curve.py
pycalibration/engine.py
pycalibration/extract.py
pycalibration/function.py
pycalibration/gearbox.py
pycalibration/map.py
pycalibration/mdf.py
pycalibration/resistance.py
pycalibration/shift.py
pycalibration/trigger.py
pycalibration/value.py
pycalibration/vbo.py
pycalibration/vehicle.py
pycalibration/watchdog.py
pycalibration-1.1.0.dist-info/LICENSE.txt
pycalibration-1.1.0.dist-info/METADATA
pycalibration-1.1.0.dist-info/WHEEL
pycalibration-1.1.0.dist-info/top_level.txt
pycalibration-1.1.0.dist-info/RECORD
