Metadata-Version: 2.1
Name: pycalibration
Version: 1.1.0
Summary: python calibration support
Home-page: https://gitlab.com/far-out/eeshei5hopah.git
Author: Jerome Douay
Author-email: jerome@far-out.biz
License: MIT
Project-URL: Documentation, https://gitlab.com/far-out/eeshei5hopah.git
Platform: any
Classifier: Development Status :: 4 - Beta
Classifier: Programming Language :: Python
License-File: LICENSE.txt
Requires-Dist: numpy
Requires-Dist: pandas
Requires-Dist: pwlf
Requires-Dist: scipy
Requires-Dist: ply
Requires-Dist: mdfreader
Requires-Dist: progressbar2
Requires-Dist: watchdog
Requires-Dist: tabulate
Requires-Dist: importlib-metadata ; python_version < "3.8"
Provides-Extra: testing
Requires-Dist: setuptools ; extra == 'testing'
Requires-Dist: pytest ; extra == 'testing'
Requires-Dist: pytest-cov ; extra == 'testing'
